st_selection_tree/__init__.py
st_selection_tree/frontend/build/asset-manifest.json
st_selection_tree/frontend/build/bootstrap.min.css
st_selection_tree/frontend/build/index.html
st_selection_tree/frontend/build/precache-manifest.9e0ff9a4cbd1629875c040c018bdc205.js
st_selection_tree/frontend/build/react-checkbox-tree.css
st_selection_tree/frontend/build/service-worker.js
st_selection_tree/frontend/build/font-awesome/css/font-awesome.css
st_selection_tree/frontend/build/font-awesome/css/font-awesome.min.css
st_selection_tree/frontend/build/font-awesome/fonts/FontAwesome.otf
st_selection_tree/frontend/build/font-awesome/fonts/fontawesome-webfont.eot
st_selection_tree/frontend/build/font-awesome/fonts/fontawesome-webfont.svg
st_selection_tree/frontend/build/font-awesome/fonts/fontawesome-webfont.ttf
st_selection_tree/frontend/build/font-awesome/fonts/fontawesome-webfont.woff
st_selection_tree/frontend/build/font-awesome/fonts/fontawesome-webfont.woff2
st_selection_tree/frontend/build/font-awesome/less/animated.less
st_selection_tree/frontend/build/font-awesome/less/bordered-pulled.less
st_selection_tree/frontend/build/font-awesome/less/core.less
st_selection_tree/frontend/build/font-awesome/less/fixed-width.less
st_selection_tree/frontend/build/font-awesome/less/font-awesome.less
st_selection_tree/frontend/build/font-awesome/less/icons.less
st_selection_tree/frontend/build/font-awesome/less/larger.less
st_selection_tree/frontend/build/font-awesome/less/list.less
st_selection_tree/frontend/build/font-awesome/less/mixins.less
st_selection_tree/frontend/build/font-awesome/less/path.less
st_selection_tree/frontend/build/font-awesome/less/rotated-flipped.less
st_selection_tree/frontend/build/font-awesome/less/screen-reader.less
st_selection_tree/frontend/build/font-awesome/less/stacked.less
st_selection_tree/frontend/build/font-awesome/less/variables.less
st_selection_tree/frontend/build/font-awesome/scss/_animated.scss
st_selection_tree-0.0.8.dist-info/LICENSE
st_selection_tree-0.0.8.dist-info/METADATA
st_selection_tree-0.0.8.dist-info/WHEEL
st_selection_tree-0.0.8.dist-info/top_level.txt
st_selection_tree-0.0.8.dist-info/RECORD
