Metadata-Version: 2.1
Name: st-selection-tree
Version: 0.0.8
Summary: A selection tree for Streamlit.
Home-page: 
Author: Nafaa
Author-email: 
Requires-Python: >=3.6
License-File: LICENSE
Requires-Dist: streamlit (>=0.63)
